.gitignore
CHANGES.txt
CONTRIBUTORS.txt
MANIFEST.in
README.md
README.txt
setup.py
src/collective/__init__.py
src/collective.zestreleaser.aftercheckoutaction.egg-info/PKG-INFO
src/collective.zestreleaser.aftercheckoutaction.egg-info/SOURCES.txt
src/collective.zestreleaser.aftercheckoutaction.egg-info/dependency_links.txt
src/collective.zestreleaser.aftercheckoutaction.egg-info/entry_points.txt
src/collective.zestreleaser.aftercheckoutaction.egg-info/namespace_packages.txt
src/collective.zestreleaser.aftercheckoutaction.egg-info/not-zip-safe
src/collective.zestreleaser.aftercheckoutaction.egg-info/requires.txt
src/collective.zestreleaser.aftercheckoutaction.egg-info/top_level.txt
src/collective/zestreleaser/__init__.py
src/collective/zestreleaser/aftercheckoutaction/__init__.py